EpicLogger/__init__.py
EpicLogger/logger.py
EpicLogger/multiprocess_handler.py
epic_logger-1.0.2.dist-info/METADATA
epic_logger-1.0.2.dist-info/WHEEL
epic_logger-1.0.2.dist-info/top_level.txt
epic_logger-1.0.2.dist-info/RECORD
