Metadata-Version: 2.1
Name: epic-logger
Version: 1.0.2
Summary: Write logs of multi-module programs to different files
Home-page: https://github.com/zerone40
Author: ZERONE40
Author-email: zerone40@163.com
License: UNKNOWN
Platform: UNKNOWN
Classifier: Programming Language :: Python :: 3
Classifier: License :: OSI Approved :: MIT License
Classifier: Operating System :: OS Independent
